package aP;

import az.JDialogExtensionInAzPackage;

class ApComponentDz extends Thread {
  ApComponentDz(
      dy paramdy,
      String paramString1,
      String paramString2,
      String paramString3,
      String paramString4,
      String paramString5,
      String paramString6,
      JDialogExtensionInAzPackage parama) {}

  public void run() {
    // Byte code:
    //   0: ldc2_w 200
    //   3: invokestatic sleep : (J)V
    //   6: goto -> 26
    //   9: astore_1
    //   10: ldc aP/dl
    //   12: invokevirtual getName : ()Ljava/lang/String;
    //   15: invokestatic getLogger : (Ljava/lang/String;)Ljava/util/logging/Logger;
    //   18: getstatic java/util/logging/Level.SEVERE : Ljava/util/logging/Level;
    //   21: aconst_null
    //   22: aload_1
    //   23: invokevirtual log : (Ljava/util/logging/Level;Ljava/lang/String;Ljava/lang/Throwable;)V
    //   26: aload_0
    //   27: getfield h : LaP/dy;
    //   30: getfield JDialogExtensionInAzPackage : LaP/dl;
    //   33: aload_0
    //   34: getfield JDialogExtensionInAzPackage : Ljava/lang/String;
    //   37: aload_0
    //   38: getfield b : Ljava/lang/String;
    //   41: aload_0
    //   42: getfield c : Ljava/lang/String;
    //   45: aload_0
    //   46: getfield d : Ljava/lang/String;
    //   49: aload_0
    //   50: getfield e : Ljava/lang/String;
    //   53: invokevirtual JDialogExtensionInAzPackage :
    // (Ljava/lang/String;Ljava/lang/String;Ljava/lang/String;Ljava/lang/String;Ljava/lang/String;)Z
    //   56: ifeq -> 128
    //   59: ldc 'The registration information provided is not valid.\\nPlease obtain
    // JDialogExtensionInAzPackage valid registion. '
    //   61: aload_0
    //   62: getfield h : LaP/dy;
    //   65: getfield JDialogExtensionInAzPackage : LaP/dl;
    //   68: invokestatic c : (LaP/dl;)Ljavax/swing/JRootPane;
    //   71: invokestatic d : (Ljava/lang/String;Ljava/awt/Component;)V
    //   74: new java/lang/StringBuilder
    //   77: dup
    //   78: invokespecial <init> : ()V
    //   81: ldc 'https://www.efianalytics.com/register/register.jsp?appName='
    //   83: invokevirtual append : (Ljava/lang/String;)Ljava/lang/StringBuilder;
    //   86: getstatic r/JDialogExtensionInAzPackage.b : Ljava/lang/String;
    //   89: invokevirtual append : (Ljava/lang/String;)Ljava/lang/StringBuilder;
    //   92: aload_0
    //   93: getfield e : Ljava/lang/String;
    //   96: ldc '(Beta)'
    //   98: ldc ''
    //   100: invokestatic b :
    // (Ljava/lang/String;Ljava/lang/String;Ljava/lang/String;)Ljava/lang/String;
    //   103: invokevirtual append : (Ljava/lang/String;)Ljava/lang/StringBuilder;
    //   106: invokevirtual toString : ()Ljava/lang/String;
    //   109: invokestatic JDialogExtensionInAzPackage : (Ljava/lang/String;)V
    //   112: aload_0
    //   113: getfield g : Laz/JDialogExtensionInAzPackage;
    //   116: iconst_0
    //   117: invokevirtual setVisible : (Z)V
    //   120: aload_0
    //   121: getfield g : Laz/JDialogExtensionInAzPackage;
    //   124: invokevirtual dispose : ()V
    //   127: return
    //   128: goto -> 132
    //   131: astore_1
    //   132: invokestatic JDialogExtensionInAzPackage : ()Lr/JDialogExtensionInAzPackage;
    //   135: getstatic r/JDialogExtensionInAzPackage.s : Ljava/lang/String;
    //   138: ldc ''
    //   140: invokevirtual b : (Ljava/lang/String;Ljava/lang/String;)V
    //   143: invokestatic JDialogExtensionInAzPackage : ()Lr/JDialogExtensionInAzPackage;
    //   146: getstatic r/JDialogExtensionInAzPackage.cF : Ljava/lang/String;
    //   149: aconst_null
    //   150: invokevirtual c : (Ljava/lang/String;Ljava/lang/String;)Ljava/lang/String;
    //   153: astore_1
    //   154: invokestatic JDialogExtensionInAzPackage : ()Lr/JDialogExtensionInAzPackage;
    //   157: getstatic r/JDialogExtensionInAzPackage.cC : Ljava/lang/String;
    //   160: aload_0
    //   161: getfield JDialogExtensionInAzPackage : Ljava/lang/String;
    //   164: invokevirtual d : (Ljava/lang/String;Ljava/lang/String;)V
    //   167: invokestatic JDialogExtensionInAzPackage : ()Lr/JDialogExtensionInAzPackage;
    //   170: getstatic r/JDialogExtensionInAzPackage.cD : Ljava/lang/String;
    //   173: aload_0
    //   174: getfield b : Ljava/lang/String;
    //   177: invokevirtual d : (Ljava/lang/String;Ljava/lang/String;)V
    //   180: invokestatic JDialogExtensionInAzPackage : ()Lr/JDialogExtensionInAzPackage;
    //   183: getstatic r/JDialogExtensionInAzPackage.cF : Ljava/lang/String;
    //   186: aload_0
    //   187: getfield c : Ljava/lang/String;
    //   190: invokevirtual d : (Ljava/lang/String;Ljava/lang/String;)V
    //   193: invokestatic JDialogExtensionInAzPackage : ()Lr/JDialogExtensionInAzPackage;
    //   196: getstatic r/JDialogExtensionInAzPackage.cE : Ljava/lang/String;
    //   199: aload_0
    //   200: getfield d : Ljava/lang/String;
    //   203: invokevirtual d : (Ljava/lang/String;Ljava/lang/String;)V
    //   206: invokestatic JDialogExtensionInAzPackage : ()Lr/JDialogExtensionInAzPackage;
    //   209: getstatic r/JDialogExtensionInAzPackage.n : Ljava/lang/String;
    //   212: aload_0
    //   213: getfield e : Ljava/lang/String;
    //   216: invokevirtual d : (Ljava/lang/String;Ljava/lang/String;)V
    //   219: aload_0
    //   220: getfield f : Ljava/lang/String;
    //   223: ifnull -> 239
    //   226: invokestatic JDialogExtensionInAzPackage : ()Lr/JDialogExtensionInAzPackage;
    //   229: getstatic r/JDialogExtensionInAzPackage.o : Ljava/lang/String;
    //   232: aload_0
    //   233: getfield f : Ljava/lang/String;
    //   236: invokevirtual d : (Ljava/lang/String;Ljava/lang/String;)V
    //   239: invokestatic JDialogExtensionInAzPackage : ()Lr/JDialogExtensionInAzPackage;
    //   242: getstatic r/JDialogExtensionInAzPackage.cL : Ljava/lang/String;
    //   245: ldc 'false'
    //   247: invokevirtual b : (Ljava/lang/String;Ljava/lang/String;)V
    //   250: aload_1
    //   251: ifnull -> 271
    //   254: aload_1
    //   255: invokevirtual isEmpty : ()Z
    //   258: ifne -> 271
    //   261: invokestatic JDialogExtensionInAzPackage : ()Lr/JDialogExtensionInAzPackage;
    //   264: getstatic r/JDialogExtensionInAzPackage.cI : Ljava/lang/String;
    //   267: aload_1
    //   268: invokevirtual d : (Ljava/lang/String;Ljava/lang/String;)V
    //   271: invokestatic JDialogExtensionInAzPackage : ()Lr/JDialogExtensionInAzPackage;
    //   274: invokevirtual i : ()V
    //   277: goto -> 309
    //   280: astore_2
    //   281: ldc 'Failed to save Registration Information.'
    //   283: aload_2
    //   284: invokestatic JDialogExtensionInAzPackage : ()LaP/dd;
    //   287: invokevirtual c : ()Ljavax/swing/JFrame;
    //   290: invokestatic JDialogExtensionInAzPackage :
    // (Ljava/lang/String;Ljava/lang/Exception;Ljava/lang/Object;)V
    //   293: aload_0
    //   294: getfield g : Laz/JDialogExtensionInAzPackage;
    //   297: iconst_0
    //   298: invokevirtual setVisible : (Z)V
    //   301: aload_0
    //   302: getfield g : Laz/JDialogExtensionInAzPackage;
    //   305: invokevirtual dispose : ()V
    //   308: return
    //   309: aload_0
    //   310: getfield h : LaP/dy;
    //   313: getfield JDialogExtensionInAzPackage : LaP/dl;
    //   316: invokestatic d : (LaP/dl;)Z
    //   319: ifeq -> 396
    //   322: new java/lang/StringBuilder
    //   325: dup
    //   326: invokespecial <init> : ()V
    //   329: ldc 'All '
    //   331: invokevirtual append : (Ljava/lang/String;)Ljava/lang/StringBuilder;
    //   334: getstatic r/JDialogExtensionInAzPackage.b : Ljava/lang/String;
    //   337: invokevirtual append : (Ljava/lang/String;)Ljava/lang/StringBuilder;
    //   340: ldc ' '
    //   342: invokevirtual append : (Ljava/lang/String;)Ljava/lang/StringBuilder;
    //   345: aload_0
    //   346: getfield e : Ljava/lang/String;
    //   349: invokevirtual append : (Ljava/lang/String;)Ljava/lang/StringBuilder;
    //   352: ldc ' features will be enabled after restarting '
    //   354: invokevirtual append : (Ljava/lang/String;)Ljava/lang/StringBuilder;
    //   357: getstatic r/JDialogExtensionInAzPackage.b : Ljava/lang/String;
    //   360: invokevirtual append : (Ljava/lang/String;)Ljava/lang/StringBuilder;
    //   363: ldc '.\\n\\nWould you like to restart Now?'
    //   365: invokevirtual append : (Ljava/lang/String;)Ljava/lang/StringBuilder;
    //   368: invokevirtual toString : ()Ljava/lang/String;
    //   371: invokestatic JDialogExtensionInAzPackage : ()LaP/dd;
    //   374: invokevirtual c : ()Ljavax/swing/JFrame;
    //   377: iconst_1
    //   378: invokestatic JDialogExtensionInAzPackage : (Ljava/lang/String;Ljava/awt/Component;Z)Z
    //   381: ifeq -> 396
    //   384: invokestatic JDialogExtensionInAzPackage : ()LaP/f;
    //   387: invokestatic JDialogExtensionInAzPackage : ()LaP/dd;
    //   390: invokevirtual c : ()Ljavax/swing/JFrame;
    //   393: invokevirtual d : (Ljava/awt/Window;)V
    //   396: aload_0
    //   397: getfield g : Laz/JDialogExtensionInAzPackage;
    //   400: iconst_0
    //   401: invokevirtual setVisible : (Z)V
    //   404: aload_0
    //   405: getfield g : Laz/JDialogExtensionInAzPackage;
    //   408: invokevirtual dispose : ()V
    //   411: goto -> 432
    //   414: astore_3
    //   415: aload_0
    //   416: getfield g : Laz/JDialogExtensionInAzPackage;
    //   419: iconst_0
    //   420: invokevirtual setVisible : (Z)V
    //   423: aload_0
    //   424: getfield g : Laz/JDialogExtensionInAzPackage;
    //   427: invokevirtual dispose : ()V
    //   430: aload_3
    //   431: athrow
    //   432: return
    // Exception table:
    //   from	to	target	type
    //   0	6	9	java/lang/InterruptedException
    //   26	112	131	V/JDialogExtensionInAzPackage
    //   26	112	414	finally
    //   128	293	414	finally
    //   271	277	280	V/JDialogExtensionInAzPackage
    //   309	396	414	finally
  }
}

/* Location:              /home/rewrich/Downloads/TunerStudioMS/TunerStudioMS/!/aP/dz.class
 * Java compiler version: 8 (52.0)
 * JD-Core Version:       1.1.3
 */
